juster/__init__.py
juster/juster.py
juster-0.1.2.dist-info/LICENSE.txt
juster-0.1.2.dist-info/METADATA
juster-0.1.2.dist-info/WHEEL
juster-0.1.2.dist-info/top_level.txt
juster-0.1.2.dist-info/RECORD
