Metadata-Version: 2.1
Name: juster
Version: 0.1.2
Summary: justification script
Home-page: https://github.com/streanger/juster
Author: streanger
Author-email: divisionexe@gmail.com
License: MIT
Platform: UNKNOWN
Classifier: Programming Language :: Python :: 3
Classifier: License :: OSI Approved :: MIT License
Classifier: Operating System :: OS Independent
